<?xml version = '1.0' encoding = 'UTF-8'?>
<Relation class="oracle.dbtools.crest.model.design.logical.Relation" name="Relation_4" directorySegmentName="seg_0" id="D8D4714A-057A-29AE-F8E8-153891A32503">
<createdBy>jhonatan</createdBy>
<createdTime>2024-06-13 17:57:52 UTC</createdTime>
<ownerDesignName>caso3</ownerDesignName>
<engineerTo>
<item key="79C54ADA-01EF-0438-43DE-734D73E658EE" value="true"/>
</engineerTo>
<sourcePk>53EE9638-D1A4-0C4F-4C15-E136CE0FA110</sourcePk>
<identifying>true</identifying>
<optionalSource>true</optionalSource>
<optionalTarget>false</optionalTarget>
<sourceCardinality>1</sourceCardinality>
<sourceEntity>B59D573D-D80A-03B7-2239-33DE1D4C3782</sourceEntity>
<targetCardinalityString>*</targetCardinalityString>
<targetEntity>9EB09F38-D637-7189-7DC3-0AF384F1C3C0</targetEntity>
<transferable>true</transferable>
<deleteRule>NO ACTION</deleteRule>
</Relation>
